sep005_io_24sea_influxdb/__init__.py
sep005_io_24sea_influxdb/influxdb.py
sep005_io_24sea_influxdb/utils.py
sep005_io_24sea_influxdb-0.0.2.dist-info/METADATA
sep005_io_24sea_influxdb-0.0.2.dist-info/WHEEL
sep005_io_24sea_influxdb-0.0.2.dist-info/top_level.txt
sep005_io_24sea_influxdb-0.0.2.dist-info/RECORD
