Metadata-Version: 2.1
Name: sep005_io_24sea_influxdb
Version: 0.0.2
Summary: Collect raw timeseries data from 24SEA influxdb, compliant with SDyPy SEP005
Home-page: https://github.com/OWI-Lab
Author: Wout Weijtjens
Author-email: wout.weijtjens@24sea.eu
Maintainer: Wout Weijtjens
Maintainer-email: wout.weijtjens@24sea.eu
License: MIT license
Keywords: io,influxdb,SEP005
Classifier: Development Status :: 3 - Alpha
Classifier: Intended Audience :: Developers
Classifier: Programming Language :: Python :: 3.6
